Metadata-Version: 2.4
Name: odoo-addon-marginalized_groups_somconnexio
Version: 16.0.1.0.0
Summary: Customizations for marginalized groups in Som Connexió.
Home-page: https://coopdevs.org
Author: Coopdevs Treball SCCL, Som Connexió SCCL
License: AGPL-3
Classifier: Programming Language :: Python
Classifier: Framework :: Odoo
Classifier: Framework :: Odoo :: 16.0
Classifier: License :: OSI Approved :: GNU Affero General Public License v3
Requires-Python: >=3.10
Requires-Dist: odoo-addon-cooperator_somconnexio<16.1dev,>=16.0dev
Requires-Dist: odoo<16.1dev,>=16.0a
Dynamic: author
Dynamic: classifier
Dynamic: description
Dynamic: home-page
Dynamic: license
Dynamic: requires-dist
Dynamic: requires-python
Dynamic: summary
